pykawos/__init__.py
pykawos/mapper.py
pykawos-0.0.3.dist-info/METADATA
pykawos-0.0.3.dist-info/WHEEL
pykawos-0.0.3.dist-info/top_level.txt
pykawos-0.0.3.dist-info/RECORD
