Metadata-Version: 2.1
Name: pykawos
Version: 0.0.3
Summary: Python KMA AWS and ASOS
Home-page: https://gitlab.com/dogbull/pykawos
Author: ParkJooHyeon
Author-email: www.jrr.kr@gmail.com
License: UNKNOWN
Keywords: kma,asos,aws
Platform: UNKNOWN
Classifier: Programming Language :: Python :: 3
Classifier: Programming Language :: Python :: 3.2
Classifier: Programming Language :: Python :: 3.3
Classifier: Programming Language :: Python :: 3.4
Classifier: Programming Language :: Python :: 3.5
Classifier: Programming Language :: Python :: 3.6
Classifier: Programming Language :: Python :: 3.8
Classifier: Programming Language :: Python :: 3.9
Classifier: Programming Language :: Python :: 3.10
Requires-Python: >=3
Requires-Dist: geopandas
Requires-Dist: python-dateutil
